gerrit_robo/__init__.py
gerrit_robo/gerrit_robo.py
gerrit_robo-0.0.2.dist-info/LICENSE
gerrit_robo-0.0.2.dist-info/METADATA
gerrit_robo-0.0.2.dist-info/WHEEL
gerrit_robo-0.0.2.dist-info/top_level.txt
gerrit_robo-0.0.2.dist-info/RECORD
