Metadata-Version: 2.1
Name: gerrit-robo
Version: 0.0.2
Summary: A very thin wrapper around the gerrit API to allow robots to add comments to a patchset
Home-page: https://github.com/tom-010/gerrit_robo.git
Author: Thomas Deniffel
Author-email: tdeniffel@gmail.com
License: Apache2
Platform: UNKNOWN
Classifier: Development Status :: 4 - Beta
Classifier: Intended Audience :: Developers
Classifier: Programming Language :: Python
Classifier: Programming Language :: Python :: 3 :: Only
Classifier: Programming Language :: Python :: 3.6
Classifier: Programming Language :: Python :: 3.7
Requires-Python: >=3
Requires-Dist: requests
